{"meta": {"name": "openaq-api", "license": "CC BY 4.0", "website": "https://docs.openaq.org/", "page": 1, "limit": 10000, "found": 21}, "results": [{"id": "US-139", "country": "US", "city": "Aberdeen", "cities": ["Aberdeen"], "location": "Aberdeen-Division St", "locations": ["Aberdeen-Division St"], "sourceName": "AirNow", "sourceNames": ["AirNow"], "sourceType": "government", "sourceTypes": ["government"], "coordinates": {"longitude": -123.8317, "latitude": 46.9772}, "firstUpdated": "2016-03-06T19:00:00.000Z", "lastUpdated": "2020-12-02T03:00:00.000Z", "parameters": ["pm25"], "countsByMeasurement": [{"parameter": "pm25", "count": 33745}], "count": 33745}, {"id": "US-82", "country": "US", "city": "Aberdeen", "cities": ["Aberdeen"], "location": "Taholah-Quinault Tri", "locations": ["Taholah-Quinault Tri"], "sourceName": "AirNow", "sourceNames": ["AirNow"], "sourceType": "government", "sourceTypes": ["government"], "coordinates": {"longitude": -124.2918, "latitude": 47.3398}, "firstUpdated": "2016-03-06T19:00:00.000Z", "lastUpdated": "2020-12-02T03:00:00.000Z", "parameters": ["pm25"], "countsByMeasurement": [{"parameter": "pm25", "count": 20074}], "count": 20074}, {"id": "US-126", "country": "US", "city": "CLARK", "cities": ["CLARK"], "location": "Vancouver-NE 84th Av", "locations": ["Vancouver-NE 84th Av"], "sourceName": "AirNow", "sourceNames": ["AirNow"], "sourceType": "government", "sourceTypes": ["government"], "coordinates": {"longitude": -122.58737, "latitude": 45.64336}, "firstUpdated": "2016-03-06T19:00:00.000Z", "lastUpdated": "2020-12-02T03:00:00.000Z", "parameters": ["pm25"], "countsByMeasurement": [{"parameter": "pm25", "count": 34375}], "count": 34375}, {"id": "US-89", "country": "US", "city": "CLARK", "cities": ["CLARK"], "location": "Yacolt-Yacolt Rd", "locations": ["Yacolt-Yacolt Rd"], "sourceName": "AirNow", "sourceNames": ["AirNow"], "sourceType": "government", "sourceTypes": ["government"], "coordinates": {"longitude": -122.41089, "latitude": 45.8639}, "firstUpdated": "2016-03-06T19:00:00.000Z", "lastUpdated": "2020-12-02T03:00:00.000Z", "parameters": ["pm25"], "countsByMeasurement": [{"parameter": "pm25", "count": 33443}], "count": 33443}, {"id": "US-179", "country": "US", "city": "LEWIS", "cities": ["LEWIS"], "location": "Chehalis-Market Blvd", "locations": ["Chehalis-Market Blvd"], "sourceName": "AirNow", "sourceNames": ["AirNow"], "sourceType": "government", "sourceTypes": ["government"], "coordinates": {"longitude": -122.96732, "latitude": 46.66409}, "firstUpdated": "2016-03-06T19:00:00.000Z", "lastUpdated": "2020-12-02T03:00:00.000Z", "parameters": ["pm25"], "countsByMeasurement": [{"parameter": "pm25", "count": 29253}], "count": 29253}, {"id": "US-153", "country": "US", "city": "Longview", "cities": ["Longview"], "location": "Longview-30th Ave", "locations": ["Longview-30th Ave"], "sourceName": "AirNow", "sourceNames": ["AirNow"], "sourceType": "government", "sourceTypes": ["government"], "coordinates": {"longitude": -122.9619, "latitude": 46.1394}, "firstUpdated": "2016-03-06T19:00:00.000Z", "lastUpdated": "2020-12-02T03:00:00.000Z", "parameters": ["pm25"], "countsByMeasurement": [{"parameter": "pm25", "count": 33365}], "count": 33365}, {"id": "US-2082", "country": "US", "city": "MULTNOMAH", "cities": ["MULTNOMAH"], "location": "Gresham", "locations": ["Gresham"], "sourceName": "AirNow", "sourceNames": ["AirNow"], "sourceType": "government", "sourceTypes": ["government"], "coordinates": {"longitude": -122.48203, "latitude": 45.51199}, "firstUpdated": "2017-08-11T01:00:00.000Z", "lastUpdated": "2018-05-10T17:00:00.000Z", "parameters": ["pm25"], "countsByMeasurement": [{"parameter": "pm25", "count": 2023}], "count": 2023}, {"id": "US-4696", "country": "US", "city": "MULTNOMAH", "cities": ["MULTNOMAH"], "location": "Gresham Centennial H", "locations": ["Gresham Centennial H"], "sourceName": "AirNow", "sourceNames": ["AirNow"], "sourceType": "government", "sourceTypes": ["government"], "coordinates": {"longitude": -122.4834, "latitude": 45.4962}, "firstUpdated": "2020-07-09T20:00:00.000Z", "lastUpdated": "2020-12-02T04:00:00.000Z", "parameters": ["pm25"], "countsByMeasurement": [{"parameter": "pm25", "count": 4803}], "count": 4803}, {"id": "US-121", "country": "US", "city": "Olympia", "cities": ["Olympia"], "location": "Lacey-College St", "locations": ["Lacey-College St"], "sourceName": "AirNow", "sourceNames": ["AirNow"], "sourceType": "government", "sourceTypes": ["government"], "coordinates": {"longitude": -122.8215, "latitude": 47.0293}, "firstUpdated": "2016-03-06T19:00:00.000Z", "lastUpdated": "2020-12-02T03:00:00.000Z", "parameters": ["pm25"], "countsByMeasurement": [{"parameter": "pm25", "count": 35673}], "count": 35673}, {"id": "US-3640", "country": "US", "city": "PACIFIC", "cities": ["PACIFIC"], "location": "Raymond-4th St", "locations": ["Raymond-4th St"], "sourceName": "AirNow", "sourceNames": ["AirNow"], "sourceType": "government", "sourceTypes": ["government"], "coordinates": {"longitude": -123.73177, "latitude": 46.68822}, "firstUpdated": "2019-10-17T13:00:00.000Z", "lastUpdated": "2020-12-02T03:00:00.000Z", "parameters": ["pm25"], "countsByMeasurement": [{"parameter": "pm25", "count": 9989}], "count": 9989}, {"id": "US-2745", "country": "US", "city": "PACIFIC", "cities": ["PACIFIC"], "location": "South Bend - First S", "locations": ["South Bend - First S", "SOUFIRST"], "sourceName": "AirNow", "sourceNames": ["AirNow"], "sourceType": "government", "sourceTypes": ["government"], "coordinates": {"longitude": -123.7916, "latitude": 46.66186}, "firstUpdated": "2018-07-23T22:00:00.000Z", "lastUpdated": "2019-07-25T17:00:00.000Z", "parameters": ["pm25"], "countsByMeasurement": [{"parameter": "pm25", "count": 7541}], "count": 7541}, {"id": "US-1295", "country": "US", "city": "Portland-Vancouver-Beaverton", "cities": ["Portland-Vancouver-Beaverton"], "location": "Beaverton - Highland", "locations": ["Beaverton - Highland"], "sourceName": "AirNow", "sourceNames": ["AirNow"], "sourceType": "government", "sourceTypes": ["government"], "coordinates": {"longitude": -122.8159, "latitude": 45.4702}, "firstUpdated": "2016-03-10T08:00:00.000Z", "lastUpdated": "2020-12-02T04:00:00.000Z", "parameters": ["pm25"], "countsByMeasurement": [{"parameter": "pm25", "count": 28793}], "count": 28793}, {"id": "US-1275", "country": "US", "city": "Portland-Vancouver-Beaverton", "cities": ["Portland-Vancouver-Beaverton"], "location": "Hillsboro - Hare Fie", "locations": ["Hillsboro - Hare Fie"], "sourceName": "AirNow", "sourceNames": ["AirNow"], "sourceType": "government", "sourceTypes": ["government"], "coordinates": {"longitude": -122.9724, "latitude": 45.5285}, "firstUpdated": "2016-03-10T08:00:00.000Z", "lastUpdated": "2020-12-02T04:00:00.000Z", "parameters": ["pm25"], "countsByMeasurement": [{"parameter": "pm25", "count": 29142}], "count": 29142}, {"id": "US-4552", "country": "US", "city": "Portland-Vancouver-Beaverton", "cities": ["Portland-Vancouver-Beaverton"], "location": "Portland Cully Helen", "locations": ["Portland Cully Helen"], "sourceName": "AirNow", "sourceNames": ["AirNow"], "sourceType": "government", "sourceTypes": ["government"], "coordinates": {"longitude": -122.57562, "latitude": 45.5622}, "firstUpdated": "2020-03-27T23:00:00.000Z", "lastUpdated": "2020-12-02T04:00:00.000Z", "parameters": ["bc", "pm25"], "countsByMeasurement": [{"parameter": "bc", "count": 7316}, {"parameter": "pm25", "count": 7469}], "count": 14785}, {"id": "US-4551", "country": "US", "city": "Portland-Vancouver-Beaverton", "cities": ["MULTNOMAH", "Portland-Vancouver-Beaverton"], "location": "Portland Humboldt Sc", "locations": ["Portland Humboldt Sc"], "sourceName": "AirNow", "sourceNames": ["AirNow"], "sourceType": "government", "sourceTypes": ["government"], "coordinates": {"longitude": -122.67098, "latitude": 45.55808}, "firstUpdated": "2020-03-27T22:00:00.000Z", "lastUpdated": "2020-12-02T04:00:00.000Z", "parameters": ["bc", "pm25"], "countsByMeasurement": [{"parameter": "bc", "count": 7115}, {"parameter": "pm25", "count": 4592}], "count": 11707}, {"id": "US-1296", "country": "US", "city": "Portland-Vancouver-Beaverton", "cities": ["Portland-Vancouver-Beaverton"], "location": "Portland Near Road", "locations": ["Portland Near Road"], "sourceName": "AirNow", "sourceNames": ["AirNow"], "sourceType": "government", "sourceTypes": ["government"], "coordinates": {"longitude": -122.7455, "latitude": 45.39916}, "firstUpdated": "2016-03-10T08:00:00.000Z", "lastUpdated": "2020-12-02T04:00:00.000Z", "parameters": ["bc", "co", "no2", "o3", "pm25"], "countsByMeasurement": [{"parameter": "bc", "count": 19115}, {"parameter": "co", "count": 16938}, {"parameter": "no2", "count": 27850}, {"parameter": "o3", "count": 27674}, {"parameter": "pm25", "count": 17892}], "count": 109469}, {"id": "US-1282", "country": "US", "city": "Portland-Vancouver-Beaverton", "cities": ["Portland-Vancouver-Beaverton"], "location": "Portland - Sauvie Is", "locations": ["Portland - Sauvie Is"], "sourceName": "AirNow", "sourceNames": ["AirNow"], "sourceType": "government", "sourceTypes": ["government"], "coordinates": {"longitude": -122.7721, "latitude": 45.76853}, "firstUpdated": "2016-03-10T08:00:00.000Z", "lastUpdated": "2020-12-02T04:00:00.000Z", "parameters": ["o3", "pm25"], "countsByMeasurement": [{"parameter": "o3", "count": 14171}, {"parameter": "pm25", "count": 28188}], "count": 42359}, {"id": "US-1272", "country": "US", "city": "Portland-Vancouver-Beaverton", "cities": ["Portland-Vancouver-Beaverton"], "location": "Portland - SE Lafaye", "locations": ["Portland - SE Lafaye"], "sourceName": "AirNow", "sourceNames": ["AirNow"], "sourceType": "government", "sourceTypes": ["government"], "coordinates": {"longitude": -122.60287, "latitude": 45.49664}, "firstUpdated": "2016-03-10T08:00:00.000Z", "lastUpdated": "2020-12-02T04:00:00.000Z", "parameters": ["bc", "co", "no2", "o3", "pm25", "so2"], "countsByMeasurement": [{"parameter": "bc", "count": 7439}, {"parameter": "co", "count": 16526}, {"parameter": "no2", "count": 27858}, {"parameter": "o3", "count": 28282}, {"parameter": "pm25", "count": 28897}, {"parameter": "so2", "count": 26595}], "count": 135597}, {"id": "US-202", "country": "US", "city": "Shelton", "cities": ["Shelton"], "location": "Shelton-W Franklin", "locations": ["Shelton-W Franklin"], "sourceName": "AirNow", "sourceNames": ["AirNow"], "sourceType": "government", "sourceTypes": ["government"], "coordinates": {"longitude": -123.10081, "latitude": 47.21355}, "firstUpdated": "2016-03-06T19:00:00.000Z", "lastUpdated": "2020-12-02T03:00:00.000Z", "parameters": ["pm25"], "countsByMeasurement": [{"parameter": "pm25", "count": 33703}], "count": 33703}, {"id": "US-4716", "country": "US", "city": "TILLAMOOK", "cities": ["TILLAMOOK"], "location": "Tillamook Forestry D", "locations": ["Tillamook Forestry D"], "sourceName": "AirNow", "sourceNames": ["AirNow"], "sourceType": "government", "sourceTypes": ["government"], "coordinates": {"longitude": -123.80281, "latitude": 45.45735}, "firstUpdated": "2020-07-23T20:00:00.000Z", "lastUpdated": "2020-12-02T04:00:00.000Z", "parameters": ["pm25"], "countsByMeasurement": [{"parameter": "pm25", "count": 3847}], "count": 3847}, {"id": "US-4843", "country": "US", "city": "WASHINGTON", "cities": ["WASHINGTON"], "location": "Forest Grove Pacific", "locations": ["Forest Grove Pacific"], "sourceName": "AirNow", "sourceNames": ["AirNow"], "sourceType": "government", "sourceTypes": ["government"], "coordinates": {"longitude": -123.10554, "latitude": 45.52483}, "firstUpdated": "2020-09-05T02:00:00.000Z", "lastUpdated": "2020-12-02T04:00:00.000Z", "parameters": ["pm25"], "countsByMeasurement": [{"parameter": "pm25", "count": 3076}], "count": 3076}]}